sql_optimizer_python/__init__.py
sql_optimizer_python/cli.py
sql_optimizer_python/exceptions.py
sql_optimizer_python/optimizer.py
sql_optimizer_python/examples/advanced_optimization_rules.json
sql_optimizer_python/examples/basic_optimization_rules.json
sql_optimizer_python/examples/custom_table_metadata.json
sql_optimizer_python/examples/employees_metadata.json
sql_optimizer_python/examples/multiple_tables_metadata.json
sql_optimizer_python/java_assets/sql-optimizer-1.0.0.jar
sql_optimizer-1.0.3.dist-info/METADATA
sql_optimizer-1.0.3.dist-info/WHEEL
sql_optimizer-1.0.3.dist-info/entry_points.txt
sql_optimizer-1.0.3.dist-info/top_level.txt
sql_optimizer-1.0.3.dist-info/RECORD
