Metadata-Version: 2.4
Name: sql-optimizer
Version: 1.0.3
Summary: Python обертка для Java-оптимизатора SQL запросов на базе Apache Calcite
Home-page: https://github.com/sql-optimizer/sql-optimizer-python
Author: SQL Optimizer Team
Author-email: SQL Optimizer Team <team@sql-optimizer.com>
Maintainer-email: SQL Optimizer Team <team@sql-optimizer.com>
License: MIT
Project-URL: Homepage, https://github.com/sql-optimizer/sql-optimizer-python
Project-URL: Documentation, https://sql-optimizer-python.readthedocs.io/
Project-URL: Repository, https://github.com/sql-optimizer/sql-optimizer-python
Project-URL: Bug Tracker, https://github.com/sql-optimizer/sql-optimizer-python/issues
Keywords: sql,optimizer,calcite,java,database,query,optimization
Classifier: Development Status :: 4 - Beta
Classifier: Intended Audience :: Developers
Classifier: License :: OSI Approved :: MIT License
Classifier: Operating System :: OS Independent
Classifier: Programming Language :: Python :: 3
Classifier: Programming Language :: Python :: 3.8
Classifier: Programming Language :: Python :: 3.9
Classifier: Programming Language :: Python :: 3.10
Classifier: Programming Language :: Python :: 3.11
Classifier: Topic :: Database
Classifier: Topic :: Software Development :: Libraries :: Python Modules
Requires-Python: >=3.8
Provides-Extra: dev
Requires-Dist: pytest>=6.0; extra == "dev"
Requires-Dist: pytest-cov>=2.0; extra == "dev"
Requires-Dist: black>=21.0; extra == "dev"
Requires-Dist: flake8>=3.8; extra == "dev"
Requires-Dist: mypy>=0.800; extra == "dev"
Provides-Extra: docs
Requires-Dist: sphinx>=4.0; extra == "docs"
Requires-Dist: sphinx-rtd-theme>=1.0; extra == "docs"
Dynamic: author
Dynamic: home-page
Dynamic: requires-python
